sentry_rest/__init__.py
sentry_rest/client.py
sentry_rest/report.py
sentry_rest-0.0.4.dist-info/METADATA
sentry_rest-0.0.4.dist-info/WHEEL
sentry_rest-0.0.4.dist-info/entry_points.txt
sentry_rest-0.0.4.dist-info/RECORD
