Metadata-Version: 2.1
Name: sentry-rest
Version: 0.0.4
Summary: 
License: MIT
Author: Inom Turdikulov
Author-email: inom@iturdikulov.com
Requires-Python: >=3.10,<4.0
Classifier: License :: OSI Approved :: MIT License
Classifier: Programming Language :: Python :: 3
Classifier: Programming Language :: Python :: 3.10
Classifier: Programming Language :: Python :: 3.11
Classifier: Programming Language :: Python :: 3.12
Requires-Dist: aiohttp (>=3.9,<4.0)
Requires-Dist: backoff (>=2.0,<3.0)
